my_demo_pack_ex/__init__.py
my_demo_pack_ex/my_demo_pack_ex.py
my_demo_pack_ex-0.1.0.dist-info/METADATA
my_demo_pack_ex-0.1.0.dist-info/WHEEL
my_demo_pack_ex-0.1.0.dist-info/RECORD
