Metadata-Version: 2.1
Name: my_demo_pack_ex
Version: 0.1.0
Summary: A simple hello world package
Author: Abhilash Gaurav
Author-email: abhilashgaurav003@gmail.com
Requires-Python: >=3.8,<4.0
Classifier: Programming Language :: Python :: 3
Classifier: Programming Language :: Python :: 3.8
Classifier: Programming Language :: Python :: 3.9
Classifier: Programming Language :: Python :: 3.10
Classifier: Programming Language :: Python :: 3.11
Classifier: Programming Language :: Python :: 3.12
Requires-Dist: requests (>=2.32.3,<3.0.0)
